{
  "criteria": {
    "collect": {
      "trigger": "inventory_changed",
      "conditions": {
        "items": [
          {
            "items": "brick",
            "components": {
              "item_model": "trash8"
            }
          }
        ],
        "player": {
          "team": "in_safehouse"
        }
      }
    }
  },
  "parent": "sr:collections/trash7",
  "display": {
    "show_toast": true,
    "announce_to_chat": false,
    "frame": "task",
    "icon": {
      "id": "brick",
      "count": 1,
      "components": {
        "item_model": "trash8"
      }
    },
    "hidden": true,
    "title": "打印的辞职信",
    "description": "辞职理由：‘我开始变得嗜睡，做的梦也越来越长了’"
  },
  "rewards": {
    "function": "sr:abilities/add_carry"
  }
}